broker_web/__init__.py
broker_web/apps/__init__.py
broker_web/apps/alerts/__init__.py
broker_web/apps/alerts/forms.py
broker_web/apps/alerts/urls.py
broker_web/apps/alerts/views.py
broker_web/apps/alerts/tests/__init__.py
broker_web/apps/alerts/tests/test_forms.py
broker_web/apps/alerts/tests/test_urls.py
broker_web/apps/alerts/tests/test_views.py
broker_web/apps/contact/__init__.py
broker_web/apps/contact/forms.py
broker_web/apps/contact/urls.py
broker_web/apps/contact/views.py
broker_web/apps/contact/tests/__init__.py
broker_web/apps/contact/tests/test_forms.py
broker_web/apps/contact/tests/test_urls.py
broker_web/apps/contact/tests/test_views.py
broker_web/apps/error_pages/__init__.py
broker_web/apps/error_pages/views.py
broker_web/apps/getting_started/__init__.py
broker_web/apps/getting_started/urls.py
broker_web/apps/getting_started/views.py
broker_web/apps/getting_started/tests/__init__.py
broker_web/apps/getting_started/tests/test_urls.py
broker_web/apps/getting_started/tests/test_views.py
broker_web/apps/objects/__init__.py
broker_web/apps/objects/forms.py
broker_web/apps/objects/urls.py
broker_web/apps/objects/views.py
broker_web/apps/objects/tests/__init__.py
broker_web/apps/objects/tests/test_forms.py
broker_web/apps/objects/tests/test_urls.py
broker_web/apps/objects/tests/test_views.py
broker_web/apps/signup/__init__.py
broker_web/apps/signup/admin.py
broker_web/apps/signup/forms.py
broker_web/apps/signup/managers.py
broker_web/apps/signup/models.py
broker_web/apps/signup/tokens.py
broker_web/apps/signup/urls.py
broker_web/apps/signup/views.py
broker_web/apps/signup/migrations/0001_initial.py
broker_web/apps/signup/migrations/__init__.py
broker_web/apps/signup/tests/__init__.py
broker_web/apps/signup/tests/test_forms.py
broker_web/apps/signup/tests/test_models.py
broker_web/apps/signup/tests/test_tokens.py
broker_web/apps/signup/tests/test_urls.py
broker_web/apps/signup/tests/test_views.py
broker_web/apps/subscriptions/__init__.py
tom_pittgoogle-0.1.11.dist-info/METADATA
tom_pittgoogle-0.1.11.dist-info/WHEEL
tom_pittgoogle-0.1.11.dist-info/top_level.txt
tom_pittgoogle-0.1.11.dist-info/RECORD
