Metadata-Version: 2.1
Name: tom-pittgoogle
Version: 0.1.11
Summary: Pitt-Google broker module for the TOM Toolkit
Home-page: UNKNOWN
Author: Troy Raen
Author-email: troy.raen@pitt.edu
License: UNKNOWN
Keywords: astronomy,alert broker
Platform: UNKNOWN
Classifier: Development Status :: 3 - Alpha
Classifier: Intended Audience :: Developers
Classifier: Topic :: Scientific/Engineering :: Astronomy
Classifier: Topic :: Scientific/Engineering :: Physics
Classifier: License :: OSI Approved :: GNU General Public License v3 or later (GPLv3+)
Classifier: Programming Language :: Python :: 3
Classifier: Programming Language :: Python :: 3 :: Only
Requires-Python: >=3.6, <4
Requires-Dist: fastavro
Requires-Dist: google-cloud-bigquery
Requires-Dist: google-cloud-logging
Requires-Dist: google-cloud-pubsub
Requires-Dist: google-auth-oauthlib
Requires-Dist: requests-oauthlib
Requires-Dist: tomtoolkit
Requires-Dist: whitenoise
Requires-Dist: django
Requires-Dist: django-bootstrap4
Requires-Dist: django-crispy-forms
Requires-Dist: django-environ
Requires-Dist: django-extensions
Requires-Dist: django-guardian
Requires-Dist: django-recaptcha
Requires-Dist: docutils (<0.17)
Requires-Dist: myst-parser
Requires-Dist: sphinx
Requires-Dist: sphinx-copybutton
Requires-Dist: sphinx-autodoc-typehints
Requires-Dist: sphinx-rtd-theme
